AuToGraFS-2.3.2.dist-info/DESCRIPTION.rst
AuToGraFS-2.3.2.dist-info/METADATA
AuToGraFS-2.3.2.dist-info/RECORD
AuToGraFS-2.3.2.dist-info/WHEEL
AuToGraFS-2.3.2.dist-info/metadata.json
AuToGraFS-2.3.2.dist-info/top_level.txt
autografs/__init__.py
autografs/__version__.py
autografs/autografs.py
autografs/framework.py
autografs/data/sbu/DEFAULTS.xyz
autografs/data/topologies/HermannMauguin.dat
autografs/data/topologies/custom.cgd
autografs/data/topologies/nets.cgd
autografs/data/uff/rappe.csv
autografs/data/uff/uff4mof.csv
autografs/tests/__init__.py
autografs/tests/context.py
autografs/tests/test_advanced.py
autografs/tests/test_basic.py
autografs/utils/__init__.py
autografs/utils/io.py
autografs/utils/mmanalysis.py
autografs/utils/operations.py
autografs/utils/sbu.py
autografs/utils/symmetry.py
autografs/utils/topology.py
