Metadata-Version: 2.0
Name: AuToGraFS
Version: 2.3.2
Summary: Generator for topological frameworks and chemical structures.
Home-page: https://github.com/DCoupry/autografs
Author: Damien Coupry
Author-email: damien.coupry@uni-leipzig.de
License: MIT
Platform: UNKNOWN
Classifier: License :: OSI Approved :: MIT License
Classifier: Programming Language :: Python
Classifier: Programming Language :: Python :: 3
Classifier: Programming Language :: Python :: Implementation :: CPython
Requires-Python: >=3.4.0
Requires-Dist: ase
Requires-Dist: scipy (>=0.15.0)
Requires-Dist: numpy (<1.15.0)
